upasak/__init__.py
upasak/data_sanitization/__init__.py
upasak/data_sanitization/pii-detection-patterns.yaml
upasak/data_sanitization/pii-generator-mapping.yaml
upasak/data_sanitization/pii.py
upasak/fine_tune/__init__.py
upasak/fine_tune/trainer_config.py
upasak/fine_tune/training_engine.py
upasak/preprocessing/__init__.py
upasak/preprocessing/tokenizer_wrapper.py
upasak/ui/__init__.py
upasak/ui/interface.py
upasak/ui/assets/upasak_logo.png
upasak/utils/__init__.py
upasak/utils/common.py
upasak/utils/inference_template.py
upasak-0.1.1.dist-info/licenses/LICENSE
upasak-0.1.1.dist-info/METADATA
upasak-0.1.1.dist-info/WHEEL
upasak-0.1.1.dist-info/top_level.txt
upasak-0.1.1.dist-info/RECORD
