Metadata-Version: 2.4
Name: upasak
Version: 0.1.1
Summary: UI-based Fine-Tuning Framework for Large Language Models (LLMs)
Author-email: Shrut Dalwadi <shroot2702hd@gmail.com>, Raj Simpi <rajsimpi04032002@gmail.com>
License: MIT License
Project-URL: Homepage, https://github.com/shrut2702/upasak
Project-URL: Repository, https://github.com/shrut2702/upasak
Project-URL: Issues, https://github.com/shrut2702/upasak/issues
Keywords: LLM,fine-tuning,transformers,streamlit,PII-sanitization,data-governance,machine-learning,upasak,ai,nlp
Requires-Python: >=3.10
License-File: LICENSE
Requires-Dist: accelerate==1.11.0
Requires-Dist: datasets==4.2.0
Requires-Dist: transformers==4.51.0
Requires-Dist: torch==2.9.0
Requires-Dist: peft==0.15.2
Requires-Dist: streamlit==1.51.0
Requires-Dist: rstr==3.2.2
Requires-Dist: gliner==0.2.22
Requires-Dist: Faker==37.8.0
Requires-Dist: exrex==0.12.0
Requires-Dist: logger==1.4
Requires-Dist: comet-ml==3.54.1
Requires-Dist: wandb==0.23.0
Requires-Dist: matplotlib==3.10.7
Dynamic: license-file
